flamingos/__init__.py
flamingos/code.py
flamingos-0.0.1.dist-info/METADATA
flamingos-0.0.1.dist-info/WHEEL
flamingos-0.0.1.dist-info/top_level.txt
flamingos-0.0.1.dist-info/RECORD
